ament_cmake_gen_version_h/_dummy.cpython-310-x86_64-linux-gnu.so
ros_ament_cmake_gen_version_h-2.7.3.data/data/share/ament_cmake_gen_version_h/local_setup.bash
ros_ament_cmake_gen_version_h-2.7.3.data/data/share/ament_cmake_gen_version_h/local_setup.dsv
ros_ament_cmake_gen_version_h-2.7.3.data/data/share/ament_cmake_gen_version_h/local_setup.sh
ros_ament_cmake_gen_version_h-2.7.3.data/data/share/ament_cmake_gen_version_h/local_setup.zsh
ros_ament_cmake_gen_version_h-2.7.3.data/data/share/ament_cmake_gen_version_h/package.dsv
ros_ament_cmake_gen_version_h-2.7.3.data/data/share/ament_cmake_gen_version_h/package.xml
ros_ament_cmake_gen_version_h-2.7.3.data/data/share/ament_cmake_gen_version_h/cmake/ament_cmake_gen_version_h-extras.cmake
ros_ament_cmake_gen_version_h-2.7.3.data/data/share/ament_cmake_gen_version_h/cmake/ament_cmake_gen_version_h.cmake
ros_ament_cmake_gen_version_h-2.7.3.data/data/share/ament_cmake_gen_version_h/cmake/ament_cmake_gen_version_hConfig-version.cmake
ros_ament_cmake_gen_version_h-2.7.3.data/data/share/ament_cmake_gen_version_h/cmake/ament_cmake_gen_version_hConfig.cmake
ros_ament_cmake_gen_version_h-2.7.3.data/data/share/ament_cmake_gen_version_h/cmake/ament_generate_version_header.cmake
ros_ament_cmake_gen_version_h-2.7.3.data/data/share/ament_cmake_gen_version_h/cmake/generate_version_header.cmake.in
ros_ament_cmake_gen_version_h-2.7.3.data/data/share/ament_cmake_gen_version_h/cmake/version.h.in
ros_ament_cmake_gen_version_h-2.7.3.data/data/share/ament_cmake_gen_version_h/environment/ament_prefix_path.dsv
ros_ament_cmake_gen_version_h-2.7.3.data/data/share/ament_cmake_gen_version_h/environment/ament_prefix_path.sh
ros_ament_cmake_gen_version_h-2.7.3.data/data/share/ament_cmake_gen_version_h/environment/path.dsv
ros_ament_cmake_gen_version_h-2.7.3.data/data/share/ament_cmake_gen_version_h/environment/path.sh
ros_ament_cmake_gen_version_h-2.7.3.dist-info/METADATA
ros_ament_cmake_gen_version_h-2.7.3.dist-info/WHEEL
ros_ament_cmake_gen_version_h-2.7.3.dist-info/top_level.txt
ros_ament_cmake_gen_version_h-2.7.3.dist-info/RECORD
