Metadata-Version: 2.4
Name: ros-ament-cmake-gen-version-h
Version: 2.7.3
Summary: Wheel for the ament_cmake_gen_version_h (ros-ament-cmake-gen-version-h) ROS 2 package.
Dynamic: description
Dynamic: description-content-type
Dynamic: summary
